mealie_client-0.1.3.dist-info/METADATA
mealie_client-0.1.3.dist-info/WHEEL
mealie_client-0.1.3.dist-info/entry_points.txt
mealie_client-0.1.3.dist-info/licenses/LICENSE
mealie_client/__init__.py
mealie_client/auth.py
mealie_client/client.py
mealie_client/endpoints/__init__.py
mealie_client/endpoints/foods.py
mealie_client/endpoints/groups.py
mealie_client/endpoints/households.py
mealie_client/endpoints/labels.py
mealie_client/endpoints/meal_plans.py
mealie_client/endpoints/recipes.py
mealie_client/endpoints/shopping_lists.py
mealie_client/endpoints/units.py
mealie_client/endpoints/users.py
mealie_client/exceptions.py
mealie_client/models/__init__.py
mealie_client/models/common.py
mealie_client/models/food.py
mealie_client/models/group.py
mealie_client/models/household.py
mealie_client/models/label.py
mealie_client/models/meal_plan.py
mealie_client/models/recipe.py
mealie_client/models/shopping_list.py
mealie_client/models/shopping_list_item.py
mealie_client/models/unit.py
mealie_client/models/user.py
mealie_client/utils.py
mealie_client-0.1.3.dist-info/RECORD
