Metadata-Version: 2.1
Name: mealie-client
Version: 0.1.3
Summary: Unofficial Python SDK for Mealie - a self-hosted recipe manager and meal planner
Keywords: mealie,recipe,meal-planner,api,sdk,async
Author-Email: Mao Bui <maonguyen199873@gmail.com>
License: MIT
Classifier: Development Status :: 4 - Beta
Classifier: Intended Audience :: Developers
Classifier: License :: OSI Approved :: MIT License
Classifier: Operating System :: OS Independent
Classifier: Programming Language :: Python :: 3
Classifier: Programming Language :: Python :: 3.8
Classifier: Programming Language :: Python :: 3.9
Classifier: Programming Language :: Python :: 3.10
Classifier: Programming Language :: Python :: 3.11
Classifier: Programming Language :: Python :: 3.12
Classifier: Topic :: Software Development :: Libraries :: Python Modules
Classifier: Topic :: Internet :: WWW/HTTP :: Dynamic Content
Classifier: Typing :: Typed
Project-URL: Homepage, https://github.com/MaoBui2907/mealie-client
Project-URL: Repository, https://github.com/MaoBui2907/mealie-client.git
Project-URL: Documentation, https://github.com/MaoBui2907/mealie-client#readme
Project-URL: Bug Tracker, https://github.com/MaoBui2907/mealie-client/issues
Project-URL: Changelog, https://github.com/MaoBui2907/mealie-client/blob/main/CHANGELOG.md
Requires-Python: >=3.8
Requires-Dist: httpx>=0.25.0
Requires-Dist: pydantic>=2.0.0
